listen/__init__.py
listen/signal_handler.py
test/__init__.py
test/example.py
listen-0.2.1.dist-info/LICENSE
listen-0.2.1.dist-info/METADATA
listen-0.2.1.dist-info/WHEEL
listen-0.2.1.dist-info/top_level.txt
listen-0.2.1.dist-info/RECORD
