Metadata-Version: 2.1
Name: listen
Version: 0.2.1
Summary: Simple but powerful signal handling to process OS signals in python
Home-page: https://github.com/antevens/listen
Author: Antonia Stevens
Author-email: a@antevens.com
License: LICENSE
Keywords: signal,unix,kill,abort,quit,info
Platform: UNKNOWN
Classifier: Programming Language :: Python
Classifier: Programming Language :: Python :: 2
Classifier: Programming Language :: Python :: 3
Classifier: Development Status :: 4 - Beta
Classifier: Environment :: Other Environment
Classifier: Intended Audience :: Developers
Classifier: Intended Audience :: Information Technology
Classifier: Intended Audience :: System Administrators
Classifier: License :: OSI Approved :: MIT License
Classifier: Operating System :: OS Independent
Classifier: Topic :: Software Development :: Libraries :: Python Modules
